<!-- 
********************************************************************************
	Project:		GTW RPG
	Owner:			GTW Games 	
	Location:		Sweden
	Developers:		MrBrutus
	Copyrights:		See: "license.txt"
	
	Website:		http://code.albonius.com
	Version:		(git)
	Status:			Stable release
********************************************************************************
-->

<meta>
    <info author="GTWGames" name="GTWphone" type="script" description="Adds a phone where the user can select radio stations, send SMS, or call services" version="0"></info>
    <script src="phone-c.lua" type="client"></script>
    <script src="phone-s.lua" type="server"></script>
    <file src="lumia920.png" />
    <min_mta_version server="1.3.5"></min_mta_version>
</meta>
